LICENSE
README.md
setup.py
circum/__init__.py
circum/endpoint.py
circum/service.py
circum.egg-info/PKG-INFO
circum.egg-info/SOURCES.txt
circum.egg-info/dependency_links.txt
circum.egg-info/entry_points.txt
circum.egg-info/requires.txt
circum.egg-info/top_level.txt
circum/sensors/__init__.py
circum/sensors/simulator.py
circum/utils/__init__.py
circum/utils/math.py
circum/utils/network.py
circum/utils/state/__init__.py
circum/utils/state/kalman_tracker.py
circum/utils/state/simple_tracker.py
circum/utils/state/tracking.py
circum/utils/state/kalman/__init__.py
circum/utils/state/kalman/ekf.py
circum/utils/state/kalman/kalmanfilter.py
tests/circum/__init__.py
tests/circum/utils/__init__.py
tests/circum/utils/test_math.py
tests/circum/utils/state/__init__.py
tests/circum/utils/state/test_kalman_tracker.py
tests/circum/utils/state/test_simple_tracker.py
tests/circum/utils/state/test_tracking.py
tests/circum/utils/state/tracking_scenarios.py