Metadata-Version: 2.1
Name: circum
Version: 0.0.6
Summary: Circum is a set of tools for detecting and tracking moving objectsvia a variety of distributed sensors.
Home-page: https://github.com/LumineerLabs/circum
Author: Lane Haury
Author-email: lane@lumineerlabs.com
License: MIT
Platform: UNKNOWN
Classifier: License :: OSI Approved :: MIT License
Classifier: Programming Language :: Python
Classifier: Operating System :: OS Independent
Provides-Extra: lint
